opengraph/__init__.py
opengraph/opengraph.py
topicaxis_opengraph-0.5.dist-info/LICENSE.txt
topicaxis_opengraph-0.5.dist-info/METADATA
topicaxis_opengraph-0.5.dist-info/WHEEL
topicaxis_opengraph-0.5.dist-info/top_level.txt
topicaxis_opengraph-0.5.dist-info/RECORD
