Metadata-Version: 1.1
Name: topicaxis-opengraph
Version: 0.5
Summary: A module to parse the Open Graph Protocol
Home-page: https://github.com/topicaxis/opengraph
Author: Panagiotis Matigakis
Author-email: pmatigakis@gmail.com
License: MIT
Keywords: opengraph protocol facebook
Platform: UNKNOWN
Classifier: License :: OSI Approved :: MIT License
Classifier: Development Status :: 3 - Alpha
Classifier: Natural Language :: English
Classifier: Intended Audience :: Developers
Classifier: Programming Language :: Python
Classifier: Programming Language :: Python :: 3
Classifier: Programming Language :: Python :: 3.5
Classifier: Programming Language :: Python :: Implementation :: CPython
Classifier: Topic :: Text Processing :: Markup :: HTML
Classifier: Topic :: Software Development :: Libraries :: Python Modules
